py_rrc_wellbore/__init__.py
py_rrc_wellbore/cli.py
py_rrc_wellbore/mappings.py
py_rrc_wellbore/parser.py
py_rrc_wellbore-1.0.0.dist-info/licenses/LICENSE
py_rrc_wellbore-1.0.0.dist-info/METADATA
py_rrc_wellbore-1.0.0.dist-info/WHEEL
py_rrc_wellbore-1.0.0.dist-info/entry_points.txt
py_rrc_wellbore-1.0.0.dist-info/top_level.txt
py_rrc_wellbore-1.0.0.dist-info/RECORD
