Metadata-Version: 2.4
Name: py-rrc-wellbore
Version: 1.0.0
Summary: Parser for Texas RRC Well Bore dataset (EBCDIC)
Author-email: Marcus Salinas <marcus.salinas@example.com>
License: MIT License
Requires-Python: >=3.9
License-File: LICENSE
Requires-Dist: pandas
Requires-Dist: typer
Dynamic: license-file
